data_science_toolbox/__init__.py
data_science_toolbox/data_checks/__init__.py
data_science_toolbox/data_checks/dataframes/column_dtypes.py
data_science_toolbox/data_checks/dictionary/check_dictionary_keys.py
data_science_toolbox/etl/__init__.py
data_science_toolbox/etl/custom_transformers/cleaning.py
data_science_toolbox/etl/custom_transformers/DF/DF.py
data_science_toolbox/etl/custom_transformers/DF/feature_engineering.py
data_science_toolbox/gists/io/connect_to_db.py
data_science_toolbox/gists/io/connect_to_network_drive.py
data_science_toolbox/gists/io/fname_by_date.py
data_science_toolbox/gists/ml/grid_search_with_xgboost_example.py
data_science_toolbox/gists/plot_aesthetics_for_dark_themes.py
data_science_toolbox/gists/process_data.py
data_science_toolbox/gists/profile_data.py
data_science_toolbox/gists/run_notebook_report.py
data_science_toolbox/gists/timestamps.py
data_science_toolbox/io/__init__.py
data_science_toolbox/io/directory_tree.py
data_science_toolbox/io/excel_to_df_dict.py
data_science_toolbox/io/file_search_and_replace.py
data_science_toolbox/io/get_absolute_fpath.py
data_science_toolbox/io/python_config_dict.py
data_science_toolbox/io/read_data.py
data_science_toolbox/io/unique_path.py
data_science_toolbox/ml/__init__.py
data_science_toolbox/ml/feature_engineering/one_hot.py
data_science_toolbox/ml/feature_engineering/target_mean_aggregate.py
data_science_toolbox/ml/feature_list/feature_list.py
data_science_toolbox/ml/param_string_to_kwargs_dict.py
data_science_toolbox/ml/sample_weight.py
data_science_toolbox/ml/scoring/.ipynb_checkpoints/ClassMetrics-checkpoint.py
data_science_toolbox/ml/scoring/ClassMetrics.py
data_science_toolbox/pandas/__init__.py
data_science_toolbox/pandas/analysis/.ipynb_checkpoints/associative_relationship-checkpoint.py
data_science_toolbox/pandas/analysis/.ipynb_checkpoints/comparison-checkpoint.py
data_science_toolbox/pandas/analysis/.ipynb_checkpoints/difference-checkpoint.py
data_science_toolbox-0.1.4.dist-info/LICENSE
data_science_toolbox-0.1.4.dist-info/WHEEL
data_science_toolbox-0.1.4.dist-info/METADATA
data_science_toolbox-0.1.4.dist-info/RECORD
