Metadata-Version: 2.1
Name: data-science-toolbox
Version: 0.1.4
Summary: Various code to aid in data science projects for tasks involving data cleaning, ETL, EDA, NLP, viz, feature engineering, feature selection, model validation, etc.
Home-page: https://github.com/safurrier/data_science_toolbox
License: MIT
Author: safurrier
Author-email: safurrier@gmail.com
Requires-Python: >=3.6,<4.0
Classifier: License :: OSI Approved :: MIT License
Classifier: Programming Language :: Python :: 3
Classifier: Programming Language :: Python :: 3.6
Classifier: Programming Language :: Python :: 3.7
Requires-Dist: click (>=7.0,<8.0)
Requires-Dist: dask (>=2.8.1,<3.0.0)
Requires-Dist: matplotlib (>=3.0.2,<4.0.0)
Requires-Dist: numpy (>=1.15.2,<2.0.0)
Requires-Dist: openpyxl (>=3.0.1,<4.0.0)
Requires-Dist: pandas (>=0.25.3,<0.26.0)
Requires-Dist: pandas_profiling (>=2.3.0,<3.0.0)
Requires-Dist: papermill (>=1.2.1,<2.0.0)
Requires-Dist: pytest (>=5.2.4,<6.0.0)
Requires-Dist: scikit_learn (>=0.21.0,<0.22.0)
Requires-Dist: scipy (>=1.1.0,<2.0.0)
Requires-Dist: seaborn (>=0.9.0,<0.10.0)
Requires-Dist: spacy (>=2.2.3,<3.0.0)
Requires-Dist: tables (>=3.6.1,<4.0.0)
Requires-Dist: textacy (>=0.5.0,<0.6.0)
Requires-Dist: textblob (>=0.15.3,<0.16.0)
Requires-Dist: vaderSentiment (>=3.2.1,<4.0.0)
Requires-Dist: xlrd (>=1.0.0,<2.0.0)
